README.txt
setup.py
Flamebase.egg-info/PKG-INFO
Flamebase.egg-info/SOURCES.txt
Flamebase.egg-info/dependency_links.txt
Flamebase.egg-info/requires.txt
Flamebase.egg-info/top_level.txt
packages/Database.py
packages/__init__.py
packages/db.py
packages/initialize.py